<?xml version="1.0" encoding="utf-8" ?>
<Defs>
	<!-- Tanith 1st -->
	
	<ThingDef ParentName="GW_HOI_OnSkinBase">
        <defName>GW_AM_Tanith1stArmor</defName>
        <label>Tanith uniform</label>
        <description>Green fatigues combined with a carrier vest, typical fare of the Tanith First and Only. The Guardsmen of Tanith eschew armor for mobility and camouflage - their argument is that it is better to not be shot than to withstand it, and better not to be seen than to be shot at. \n\nThe Tanith First and Only is a well-accomplished regiment, with no less than three assassinations of Chaos Magisters under their collective belts.</description>
        <recipeMaker>
            <researchPrerequisite>GW_Tanith1st</researchPrerequisite>
        </recipeMaker>
        <graphicData>
            <texPath>Things/Tanith1st/Armor_Male_south</texPath>
            <graphicClass>Graphic_Single</graphicClass>
        </graphicData>
		<tickerType>Normal</tickerType>
        <costStuffCount>90</costStuffCount>
        <stuffCategories>
            <li>Fabric</li>
            <li>Leathery</li>
        </stuffCategories>
        <thingCategories>
            <li>ApparelMisc</li>
        </thingCategories>
        <statBases>
            <MaxHitPoints>220</MaxHitPoints>
            <WorkToMake>8500</WorkToMake>
			<MarketValue>150</MarketValue>
            <Mass>1.5</Mass>
            <StuffEffectMultiplierArmor>0.2</StuffEffectMultiplierArmor>
            <StuffEffectMultiplierInsulation_Cold>0.2</StuffEffectMultiplierInsulation_Cold>
            <StuffEffectMultiplierInsulation_Heat>0.3</StuffEffectMultiplierInsulation_Heat>
            <EquipDelay>3</EquipDelay>
        </statBases>
        <equippedStatOffsets>
            <SocialImpact>0.1</SocialImpact>
        </equippedStatOffsets>
        <apparel>
            <wornGraphicPath>Things/Tanith1st/Armor</wornGraphicPath>
            <tags>
                <li>40kTanith</li>
                <li>40kTanithMiddle</li>
            </tags>
        </apparel>
        <tradeTags>
            <li>HPMiddle</li>
        </tradeTags>
		<comps>
			<!-- <li Class="BM_ApparelSet.CompProperties_ApparelSet"> -->
				<!-- <apparelSetEffect> -->
					<!-- <allApparels> -->
						<!-- <li>GW_AM_Tanith1stCloak</li> -->
						<!-- <li>GW_AM_Tanith1stHood</li> -->
						<!-- <li>GW_AM_Tanith1stGoggle</li> -->
					<!-- </allApparels> -->
					<!-- <hediff>GW40k_AM_Tanith1stSet</hediff> -->
				<!-- </apparelSetEffect> -->
			<!-- </li> -->
		</comps>
    </ThingDef>  

</Defs>
